MANIFEST.in
README.rst
dev-requirements.txt
requirements.txt
setup.py
examples/basic_api_call.py
examples/basic_async_scraper.py
examples/basic_sync_scraper.py
examples/fast_async_scraper.py
examples/graphs_use_auto_timeframe.py
examples/ticker_pagination.py
precompiler/__init__.py
precompiler/builder.py
precompiler/main.py
precompiler/recopiler.py
precompiler/utils.py
pymarketcap/__init__.py
pymarketcap/consts.py
pymarketcap/core.c
pymarketcap/core.pyx
pymarketcap/curl.c
pymarketcap/curl.pxd
pymarketcap/curl.pyx
pymarketcap/errors.py
pymarketcap/processer.c
pymarketcap/processer.pyx
pymarketcap/pymasyncore.py
pymarketcap/url.py
pymarketcap/util.py
pymarketcap.egg-info/PKG-INFO
pymarketcap.egg-info/SOURCES.txt
pymarketcap.egg-info/dependency_links.txt
pymarketcap.egg-info/requires.txt
pymarketcap.egg-info/top_level.txt
pymarketcap.egg-info/zip-safe
pymarketcap/tests/__init__.py
pymarketcap/tests/consts.py
pymarketcap/tests/currency.py
pymarketcap/tests/exchange.py
pymarketcap/tests/exchanges.py
pymarketcap/tests/graphs.py
pymarketcap/tests/historical.py
pymarketcap/tests/markets.py
pymarketcap/tests/ranks.py
pymarketcap/tests/tokens.py
pymarketcap/tests/utils.py
tests/conftest.py
tests/test_examples.py
tests/test_async_core/test_async_properties.py
tests/test_async_core/test_internal_api/test_every_graphs_currency.py
tests/test_async_core/test_scraper/test_every_currency.py
tests/test_async_core/test_scraper/test_every_exchange.py
tests/test_async_core/test_scraper/test_every_historical.py
tests/test_async_core/test_scraper/test_every_markets.py
tests/test_coinmarketcap/test_endpoints.py
tests/test_processer/test_currency_parser.py
tests/test_processer/test_exchange_parser.py
tests/test_processer/test_exchanges_parser.py
tests/test_processer/test_historical_parser.py
tests/test_processer/test_markets_parser.py
tests/test_processer/test_ranks_parser.py
tests/test_processer/test_recently_parser.py
tests/test_processer/test_response_fields_consistency.py
tests/test_processer/test_tokens_parser.py
tests/test_sync_core/test_cryptocurrency_by_field_value.py
tests/test_sync_core/test_exchange_by_field_value.py
tests/test_sync_core/test_field_type.py
