Metadata-Version: 1.2
Name: pymarketcap
Version: 4.0.13
Summary: Python3 API and web scraper for coinmarketcap.com.
Home-page: https://github.com/mondeja/pymarketcap
Author: Álvaro Mondéjar Rubio
Author-email: mondejar1994@gmail.com
Maintainer: Álvaro Mondéjar Rubio
Maintainer-email: mondejar1994@gmail.com
License: BSD License
Download-URL: https://github.com/mondeja/pymarketcap/archive/master.zip
Keywords: coinmarketcap,cryptocurrency,API,wrapper,scraper,json,BTC,Bitcoin,C,Curl,Cython
Platform: any
Classifier: Development Status :: 5 - Production/Stable
Classifier: Intended Audience :: Developers
Classifier: Intended Audience :: Financial and Insurance Industry
Classifier: License :: OSI Approved :: BSD License
Classifier: Programming Language :: Python :: 3.6
Classifier: Programming Language :: Python :: 3.7
Classifier: Programming Language :: Python :: Implementation :: PyPy
Classifier: Topic :: Internet :: WWW/HTTP :: Dynamic Content
Classifier: Topic :: Office/Business
Classifier: Topic :: Office/Business :: Financial
Classifier: Topic :: Office/Business :: Financial :: Accounting
Classifier: Topic :: Office/Business :: Financial :: Investment
Classifier: Topic :: Software Development :: Libraries
Classifier: Topic :: Software Development :: Libraries :: Python Modules
Provides: setup_template_cython
